LICENCE
MANIFEST.in
README.rst
formulaparser.py
setup.py
formulaparser/__init__.py
formulaparser/api.py
formulaparser/parser.py
formulaparser/resolve.py
formulaparser.egg-info/PKG-INFO
formulaparser.egg-info/SOURCES.txt
formulaparser.egg-info/dependency_links.txt
formulaparser.egg-info/not-zip-safe
formulaparser.egg-info/requires.txt
formulaparser.egg-info/top_level.txt