Metadata-Version: 1.0
Name: formulaparser
Version: 0.0.1
Summary: Parse an arythmic formula from a string
Home-page: https://github.com/specialunderwear/python-formulaparser
Author: Lars van de Kerkhof
Author-email: lars@permanentmarkers.nl
License: GPL v3
Platform: UNKNOWN
